idf_updater/__init__.py
idf_updater/idf_updater.py
idf_updater-1.0.0.dist-info/LICENSE
idf_updater-1.0.0.dist-info/METADATA
idf_updater-1.0.0.dist-info/WHEEL
idf_updater-1.0.0.dist-info/top_level.txt
idf_updater-1.0.0.dist-info/RECORD
