Metadata-Version: 2.1
Name: idf-updater
Version: 1.0.0
Summary: A library for updating IDF files to newer versions
Home-page: https://gitlab.com/energyincities/idf_updater
Author: Ralph Evins
Author-email: revins@uvic.ca
License: UNKNOWN
Platform: UNKNOWN
Classifier: Programming Language :: Python :: 3
Classifier: License :: OSI Approved :: GNU General Public License (GPL)
Classifier: Operating System :: OS Independent
Requires-Dist: black
Requires-Dist: ipykernel
Requires-Dist: openpyxl
Requires-Dist: setuptools
Requires-Dist: pyKriging
Requires-Dist: pytest
Requires-Dist: pytest-cov
Requires-Dist: pytest-regtest
Requires-Dist: toolz
Requires-Dist: besos
